tg_archive-1.3.1.dist-info/licenses/LICENSE
tgarchive/__init__.py
tgarchive/__metadata__.py
tgarchive/build.py
tgarchive/db.py
tgarchive/sync.py
tgarchive/example/config.yaml
tgarchive/example/rss_template.html
tgarchive/example/template.html
tgarchive/example/static/favicon.png
tgarchive/example/static/logo.svg
tgarchive/example/static/main.js
tgarchive/example/static/style.css
tgarchive/example/static/thumb.png
tg_archive-1.3.1.dist-info/METADATA
tg_archive-1.3.1.dist-info/WHEEL
tg_archive-1.3.1.dist-info/entry_points.txt
tg_archive-1.3.1.dist-info/top_level.txt
tg_archive-1.3.1.dist-info/RECORD
