Metadata-Version: 2.4
Name: tg-archive
Version: 1.3.1
Summary: is a tool for exporting Telegram group chats into static websites, preserving the chat history like mailing list archives.
Home-page: https://github.com/knadh/tg-archive
Download-URL: https://github.com/knadh/tg-archive
Author: Kailash Nadh
Author-email: kailash@nadh.in
License: MIT License
Classifier: Topic :: Communications :: Chat
Classifier: Topic :: Internet :: WWW/HTTP :: Site Management
Classifier: Topic :: Documentation
License-File: LICENSE
Requires-Dist: feedgen==1.0.0
Requires-Dist: jinja2==3.1.6
Requires-Dist: lxml==5.3.1
Requires-Dist: markupsafe==3.0.2
Requires-Dist: pillow==11.1.0
Requires-Dist: pyaes==1.6.1
Requires-Dist: pyasn1==0.6.1
Requires-Dist: python-dateutil==2.9.0.post0
Requires-Dist: python-magic==0.4.27
Requires-Dist: pytz==2025.1
Requires-Dist: pyyaml==6.0.2
Requires-Dist: rsa==4.9
Requires-Dist: setuptools>=76.0.0
Requires-Dist: six==1.17.0
Requires-Dist: telethon==1.39.0
Dynamic: author
Dynamic: author-email
Dynamic: classifier
Dynamic: description
Dynamic: description-content-type
Dynamic: download-url
Dynamic: home-page
Dynamic: license
Dynamic: license-file
Dynamic: requires-dist
Dynamic: summary
